LICENSE
MANIFEST.in
README.rst
requirements.txt
setup.cfg
setup.py
test-requirements.txt
python_symphony_binding.egg-info/PKG-INFO
python_symphony_binding.egg-info/SOURCES.txt
python_symphony_binding.egg-info/dependency_links.txt
python_symphony_binding.egg-info/not-zip-safe
python_symphony_binding.egg-info/requires.txt
python_symphony_binding.egg-info/top_level.txt
symphonybinding/__init__.py
symphonybinding/data/__init__.py
symphonybinding/data/agent-api-public-deprecated.yaml
symphonybinding/data/pod-api-public-deprecated.yaml